veridica/__init__.py
veridica/batch.py
veridica/normalisation.py
veridica/similarity.py
veridica/timing.py
veridica-0.1.2.dist-info/METADATA
veridica-0.1.2.dist-info/WHEEL
veridica-0.1.2.dist-info/licenses/LICENCE
veridica-0.1.2.dist-info/RECORD
