Metadata-Version: 2.4
Name: veridica
Version: 0.1.2
Summary: Fuzzy matching for the use in gherkin based automated tests.
License: MIT
License-File: LICENCE
Author: Sebastiaan Swanenberg
Author-email: pythonveridica@gmail.com
Requires-Python: >=3.12,<4.0
Classifier: License :: OSI Approved :: MIT License
Classifier: Programming Language :: Python :: 3
Classifier: Programming Language :: Python :: 3.12
Classifier: Programming Language :: Python :: 3.13
Classifier: Programming Language :: Python :: 3.14
